{
	"name": "Write credits to db",
	"properties": {
		"activities": [
			{
				"name": "write credits to db",
				"type": "Copy",
				"dependsOn": [],
				"policy": {
					"timeout": "0.12:00:00",
					"retry": 0,
					"retryIntervalInSeconds": 30,
					"secureOutput": false,
					"secureInput": false
				},
				"userProperties": [],
				"typeProperties": {
					"source": {
						"type": "DelimitedTextSource",
						"additionalColumns": [
							{
								"name": "file_name",
								"value": "$$FILEPATH"
							},
							{
								"name": "pipeline_id",
								"value": {
									"value": "@pipeline().RunId",
									"type": "Expression"
								}
							}
						],
						"storeSettings": {
							"type": "AzureBlobFSReadSettings",
							"recursive": true,
							"wildcardFileName": "credits*",
							"enablePartitionDiscovery": false
						},
						"formatSettings": {
							"type": "DelimitedTextReadSettings"
						}
					},
					"sink": {
						"type": "AzureSqlSink",
						"preCopyScript": "truncate table [stg].[credits]",
						"writeBehavior": "insert",
						"sqlWriterUseTableLock": true,
						"disableMetricsCollection": false
					},
					"enableStaging": false,
					"enableSkipIncompatibleRow": true,
					"logSettings": {
						"enableCopyActivityLog": true,
						"copyActivityLogSettings": {
							"logLevel": "Info",
							"enableReliableLogging": false
						},
						"logLocationSettings": {
							"linkedServiceName": {
								"referenceName": "AzureDataLakeStorage1",
								"type": "LinkedServiceReference"
							},
							"path": "log"
						}
					},
					"translator": {
						"type": "TabularTranslator",
						"mappings": [
							{
								"source": {
									"name": "cast",
									"type": "String",
									"physicalType": "String"
								},
								"sink": {
									"name": "cast",
									"type": "String",
									"physicalType": "nvarchar"
								}
							},
							{
								"source": {
									"name": "crew",
									"type": "String",
									"physicalType": "String"
								},
								"sink": {
									"name": "crew",
									"type": "String",
									"physicalType": "nvarchar"
								}
							},
							{
								"source": {
									"name": "id",
									"type": "String",
									"physicalType": "String"
								},
								"sink": {
									"name": "id",
									"type": "String",
									"physicalType": "nvarchar"
								}
							},
							{
								"source": {
									"name": "pipeline_id",
									"type": "String"
								},
								"sink": {
									"name": "pipelineId",
									"type": "String",
									"physicalType": "nvarchar"
								}
							},
							{
								"source": {
									"name": "file_name",
									"type": "String"
								},
								"sink": {
									"name": "source_filename",
									"type": "String",
									"physicalType": "nvarchar"
								}
							}
						],
						"typeConversion": true,
						"typeConversionSettings": {
							"allowDataTruncation": true,
							"treatBooleanAsNumber": false
						}
					}
				},
				"inputs": [
					{
						"referenceName": "adls_raw_movies_credits",
						"type": "DatasetReference"
					}
				],
				"outputs": [
					{
						"referenceName": "MoviesDB_credits_tbl",
						"type": "DatasetReference"
					}
				]
			}
		],
		"annotations": [],
		"lastPublishTime": "2023-05-25T11:00:47Z"
	},
	"type": "Microsoft.DataFactory/factories/pipelines"
}